yoco.py
yoco-1.2.1.dist-info/licenses/LICENSE
yoco-1.2.1.dist-info/METADATA
yoco-1.2.1.dist-info/WHEEL
yoco-1.2.1.dist-info/top_level.txt
yoco-1.2.1.dist-info/RECORD
